gitlab_discord_webhook/__init__.py
gitlab_discord_webhook/__main__.py
gitlab_discord_webhook/models.py
gitlab_discord_webhook-0.2.0.dist-info/LICENSE
gitlab_discord_webhook-0.2.0.dist-info/METADATA
gitlab_discord_webhook-0.2.0.dist-info/WHEEL
gitlab_discord_webhook-0.2.0.dist-info/entry_points.txt
gitlab_discord_webhook-0.2.0.dist-info/top_level.txt
gitlab_discord_webhook-0.2.0.dist-info/RECORD
