Metadata-Version: 2.1
Name: gitlab-discord-webhook
Version: 0.2.0
Summary: A middleman between GitLab and Discord webhooks to show better formatted messages.
Author-email: Allan Galarza <allan.galarza@gmail.com>
Maintainer-email: Allan Galarza <allan.galarza@gmail.com>
License: MIT
Project-URL: Repository, https://github.com/Galarzaa90/gitlab-discord-webhook
Project-URL: GitHub: Issues, https://github.com/Galarzaa90/gitlab-discord-webhook/issues
Project-URL: Docker Hub: Repo, https://hub.docker.com/repository/docker/galarzaa90/gitlab-discord-webhook
Classifier: Development Status :: 4 - Beta
Classifier: Environment :: Console
Classifier: Intended Audience :: Developers
Classifier: License :: OSI Approved :: MIT License
Classifier: Natural Language :: English
Classifier: Operating System :: OS Independent
Classifier: Programming Language :: Python :: 3 :: Only
Classifier: Programming Language :: Python :: 3.8
Classifier: Programming Language :: Python :: 3.9
Classifier: Programming Language :: Python :: 3.10
Classifier: Programming Language :: Python :: 3.11
Classifier: Programming Language :: Python :: 3.12
Classifier: Programming Language :: Python
Classifier: Topic :: Internet
Classifier: Topic :: Software Development
Classifier: Topic :: System :: Logging
Classifier: Topic :: Utilities
Requires-Python: >=3.10
License-File: LICENSE
Requires-Dist: aiohttp ~=3.9
Requires-Dist: aiohttp-middlewares ~=2.3
Requires-Dist: discord.py ~=2.4
Requires-Dist: loguru ~=0.7
Requires-Dist: pydantic ~=2.7
Provides-Extra: lint
Requires-Dist: ruff ; extra == 'lint'
